viuvsage/__init__.py
viuvsage/cli.py
viuvsage/commands.py
viuvsage-0.1.5.dist-info/METADATA
viuvsage-0.1.5.dist-info/WHEEL
viuvsage-0.1.5.dist-info/entry_points.txt
viuvsage-0.1.5.dist-info/top_level.txt
viuvsage-0.1.5.dist-info/RECORD
