Metadata-Version: 2.4
Name: viuvsage
Version: 0.1.5
Summary: Sage: A Unified Project and Package Management System for C/C++ by viuvlabs
Author-email: Vishal Ahirwar <cvxxcv0091@gmail.com>
License: MIT
Project-URL: Homepage, https://github.com/viuvlabs/sage
Requires-Python: >=3.7
Requires-Dist: typer
Requires-Dist: rich
